{
  "_class": "symbolInstance",
  "booleanOperation": -1,
  "clippingMaskMode": 0,
  "do_objectID": "A8DADD3A-16E4-43C4-AA0E-FA4746BCF3CE",
  "exportOptions": {
    "_class": "exportOptions",
    "do_objectID": "8E6B8094-8990-4FB5-8E4D-57855268E3C2",
    "exportFormats": [
    ],
    "includedLayerIds": [
    ],
    "layerOptions": 0,
    "shouldTrim": false
  },
  "frame": {
    "_class": "rect",
    "constrainProportions": true,
    "do_objectID": "2DEC0B3C-79F5-4270-80E4-3D50737F1DE0",
    "height": 24,
    "width": 24,
    "x": 10,
    "y": 12
  },
  "hasClippingMask": false,
  "horizontalSpacing": 0,
  "isFixedToViewport": false,
  "isFlippedHorizontal": false,
  "isFlippedVertical": false,
  "isLocked": false,
  "isVisible": true,
  "layerListExpandedType": 0,
  "name": "icon / arrow-left",
  "nameIsFixed": false,
  "overrideValues": [
    {
      "_class": "overrideValue",
      "do_objectID": "7CE77568-F7A4-43B6-902D-537C9408671B",
      "overrideName": "183FE231-C36C-446F-A840-55B331435E25_symbolID",
      "value": "75E94435-BF2E-43FB-BD91-54747C649AC8"
    }
  ],
  "resizingConstraint": 63,
  "resizingType": 0,
  "rotation": 0,
  "scale": 1,
  "shouldBreakMaskChain": false,
  "style": {
    "_class": "style",
    "do_objectID": "377330AF-558B-407A-B73E-4CF036059F13",
    "endMarkerType": 0,
    "miterLimit": 10,
    "startMarkerType": 0,
    "windingRule": 1
  },
  "symbolID": "D9934861-ED5E-4D62-87D4-83DDDF0B5D97",
  "verticalSpacing": 0
}