{
  "_class": "group",
  "booleanOperation": -1,
  "clippingMaskMode": 0,
  "do_objectID": "2517B91D-0BE8-4FCC-8FB2-186A784D87B6",
  "exportOptions": {
    "_class": "exportOptions",
    "exportFormats": [
    ],
    "includedLayerIds": [
    ],
    "layerOptions": 0,
    "shouldTrim": false
  },
  "frame": {
    "_class": "rect",
    "constrainProportions": false,
    "height": 155,
    "width": 124,
    "x": 0,
    "y": 0
  },
  "hasClickThrough": false,
  "hasClippingMask": false,
  "isFixedToViewport": false,
  "isFlippedHorizontal": false,
  "isFlippedVertical": false,
  "isLocked": false,
  "isVisible": true,
  "layerListExpandedType": 2,
  "layers": [
    {
      "class": "rectangle",
      "id": "64442066-F24F-412F-9897-C573602F7862"
    },
    {
      "class": "shapeGroup",
      "id": "C603730B-7119-424E-8993-82C773653E54"
    },
    {
      "class": "shapeGroup",
      "id": "7276FFB5-75DB-42E7-9274-CDB57850962F"
    },
    {
      "class": "rectangle",
      "id": "DC04048C-B595-4ACA-8E15-A02D02D6F646"
    }
  ],
  "name": "K",
  "nameIsFixed": true,
  "resizingConstraint": 63,
  "resizingType": 0,
  "rotation": 0,
  "shouldBreakMaskChain": false,
  "style": {
    "_class": "style",
    "endMarkerType": 0,
    "miterLimit": 10,
    "startMarkerType": 0,
    "windingRule": 1
  }
}